mujopy/__init__.py
mujopy/src/__init__.py
mujopy/src/mujopy_model/__init__.py
mujopy/src/mujopy_model/body.py
mujopy/src/mujopy_model/geom.py
mujopy/src/mujopy_model/joint.py
mujopy/src/mujopy_model/mujopy_model.py
mujopy/src/mujopy_model/property_packs.py
mujopy/src/mujopy_model/utils.py
mujopy/src/robot_graph/__init__.py
mujopy/src/robot_graph/feature_processor.py
mujopy/src/robot_graph/robot_graph.py
mujopy-0.0.1.dist-info/licenses/LICENSE
mujopy-0.0.1.dist-info/METADATA
mujopy-0.0.1.dist-info/WHEEL
mujopy-0.0.1.dist-info/top_level.txt
mujopy-0.0.1.dist-info/RECORD
