Metadata-Version: 2.4
Name: mujopy
Version: 0.0.1
Summary: Pythonic wrappers for MuJoCo models and Graph representations.
Author-email: Lukas Müller <lukasbmueller@gmail.com>
License-Expression: MIT
Keywords: mujoco,robotics,graph
Classifier: Development Status :: 3 - Alpha
Classifier: Intended Audience :: Developers
Classifier: Programming Language :: Python
Classifier: Programming Language :: Python :: 3
Classifier: Programming Language :: Python :: 3 :: Only
Requires-Python: >=3.10
License-File: LICENSE
Requires-Dist: mujoco>=3.3.6
Requires-Dist: numpy>=2.3.3
Requires-Dist: networkx>=3.5
Requires-Dist: pyyaml>=6.0.3
Provides-Extra: test
Requires-Dist: pytest>=7; extra == "test"
Dynamic: license-file
